Metadata-Version: 2.1
Name: Artemix3
Version: 1.0.0
Summary: A library for Industrial Engineering
Home-page: UNKNOWN
Author: Artemio Araya
Author-email: artemioaday@gmail.com
License: MIT
Keywords: Microeconomics,Electromagnetism,Economics,Industrial Process,Calculus,Render
Platform: UNKNOWN
Classifier: Development Status :: 5 - Production/Stable
Classifier: Intended Audience :: Science/Research
Classifier: License :: OSI Approved :: GNU Lesser General Public License v2 (LGPLv2)
Classifier: Programming Language :: Python :: 3 :: Only
Classifier: Programming Language :: Python :: 3.7
Classifier: Programming Language :: Python :: 3.8
Classifier: Programming Language :: Python :: 3.9
Classifier: Topic :: Scientific/Engineering
Classifier: Topic :: Scientific/Engineering :: Artificial Intelligence
Classifier: Topic :: Scientific/Engineering :: Mathematics
